hi_hun0219/__init__.py
hi_hun0219/hello.py
hi_hun0219-0.7.4.dist-info/METADATA
hi_hun0219-0.7.4.dist-info/WHEEL
hi_hun0219-0.7.4.dist-info/entry_points.txt
hi_hun0219-0.7.4.dist-info/top_level.txt
hi_hun0219-0.7.4.dist-info/RECORD
